carooline_tecrmi_seamless/__init__.py
carooline_tecrmi_seamless/__main__.py
carooline_tecrmi_seamless/main.py
carooline_tecrmi_seamless/webcat_service.py
carooline_tecrmi_seamless-0.4.0.dist-info/entry_points.txt
carooline_tecrmi_seamless-0.4.0.dist-info/WHEEL
carooline_tecrmi_seamless-0.4.0.dist-info/METADATA
carooline_tecrmi_seamless-0.4.0.dist-info/RECORD
