Metadata-Version: 2.1
Name: carooline-tecrmi-seamless
Version: 0.4.0
Summary: 
Author: Philippe L'ATTENTION
Author-email: philippe.lattention@hotmail.fr
Requires-Python: >=3.6,<4.0
Classifier: Programming Language :: Python :: 3
Classifier: Programming Language :: Python :: 3.10
Classifier: Programming Language :: Python :: 3.6
Classifier: Programming Language :: Python :: 3.7
Classifier: Programming Language :: Python :: 3.8
Classifier: Programming Language :: Python :: 3.9
Requires-Dist: python-dotenv (>=0.19.2,<0.20.0)
Requires-Dist: typer (>=0.4.0,<0.5.0)
Requires-Dist: zeep (>=4.1.0,<5.0.0)
